setup.cfg
setup.py
keyme/__init__.py
keyme/writer.py
keyme.egg-info/PKG-INFO
keyme.egg-info/SOURCES.txt
keyme.egg-info/dependency_links.txt
keyme.egg-info/entry_points.txt
keyme.egg-info/not-zip-safe
keyme.egg-info/requires.txt
keyme.egg-info/top_level.txt
keyme/cli/__init__.py
keyme/cli/fetch_creds.py
keyme/test/__init__.py
keyme/test/test_writer.py